fsspec/__init__.py
fsspec/_version.py
fsspec/archive.py
fsspec/asyn.py
fsspec/caching.py
fsspec/callbacks.py
fsspec/compression.py
fsspec/config.py
fsspec/conftest.py
fsspec/core.py
fsspec/dircache.py
fsspec/exceptions.py
fsspec/fuse.py
fsspec/generic.py
fsspec/gui.py
fsspec/mapping.py
fsspec/parquet.py
fsspec/registry.py
fsspec/spec.py
fsspec/transaction.py
fsspec/utils.py
fsspec/implementations/__init__.py
fsspec/implementations/arrow.py
fsspec/implementations/cache_mapper.py
fsspec/implementations/cache_metadata.py
fsspec/implementations/cached.py
fsspec/implementations/dask.py
fsspec/implementations/data.py
fsspec/implementations/dbfs.py
fsspec/implementations/dirfs.py
fsspec/implementations/ftp.py
fsspec/implementations/git.py
fsspec/implementations/github.py
fsspec/implementations/http.py
fsspec/implementations/jupyter.py
fsspec/implementations/libarchive.py
fsspec/implementations/local.py
fsspec/implementations/memory.py
fsspec/implementations/reference.py
fsspec/implementations/sftp.py
fsspec/implementations/smb.py
fsspec/implementations/tar.py
fsspec/implementations/webhdfs.py
fsspec/implementations/zip.py
fsspec/tests/abstract/__init__.py
fsspec/tests/abstract/common.py
fsspec/tests/abstract/copy.py
fsspec/tests/abstract/get.py
fsspec/tests/abstract/put.py
fsspec-2024.3.0.dist-info/LICENSE
fsspec-2024.3.0.dist-info/METADATA
fsspec-2024.3.0.dist-info/WHEEL
fsspec-2024.3.0.dist-info/top_level.txt
fsspec-2024.3.0.dist-info/RECORD
