Metadata-Version: 2.1
Name: fsspec
Version: 2024.3.0
Summary: File-system specification
Home-page: https://github.com/fsspec/filesystem_spec
Maintainer: Martin Durant
Maintainer-email: mdurant@anaconda.com
License: BSD
Project-URL: Changelog, https://filesystem-spec.readthedocs.io/en/latest/changelog.html
Project-URL: Documentation, https://filesystem-spec.readthedocs.io/en/latest/
Keywords: file
Classifier: Development Status :: 4 - Beta
Classifier: Intended Audience :: Developers
Classifier: License :: OSI Approved :: BSD License
Classifier: Operating System :: OS Independent
Classifier: Programming Language :: Python :: 3.8
Classifier: Programming Language :: Python :: 3.9
Classifier: Programming Language :: Python :: 3.10
Classifier: Programming Language :: Python :: 3.11
Requires-Python: >=3.8
License-File: LICENSE
Provides-Extra: entrypoints
Provides-Extra: abfs
Requires-Dist: adlfs; extra == "abfs"
Provides-Extra: adl
Requires-Dist: adlfs; extra == "adl"
Provides-Extra: dask
Requires-Dist: dask; extra == "dask"
Requires-Dist: distributed; extra == "dask"
Provides-Extra: dropbox
Requires-Dist: dropboxdrivefs; extra == "dropbox"
Requires-Dist: requests; extra == "dropbox"
Requires-Dist: dropbox; extra == "dropbox"
Provides-Extra: gcs
Requires-Dist: gcsfs; extra == "gcs"
Provides-Extra: git
Requires-Dist: pygit2; extra == "git"
Provides-Extra: github
Requires-Dist: requests; extra == "github"
Provides-Extra: gs
Requires-Dist: gcsfs; extra == "gs"
Provides-Extra: hdfs
Requires-Dist: pyarrow>=1; extra == "hdfs"
Provides-Extra: arrow
Requires-Dist: pyarrow>=1; extra == "arrow"
Provides-Extra: http
Requires-Dist: aiohttp!=4.0.0a0,!=4.0.0a1; extra == "http"
Provides-Extra: sftp
Requires-Dist: paramiko; extra == "sftp"
Provides-Extra: s3
Requires-Dist: s3fs; extra == "s3"
Provides-Extra: oci
Requires-Dist: ocifs; extra == "oci"
Provides-Extra: smb
Requires-Dist: smbprotocol; extra == "smb"
Provides-Extra: ssh
Requires-Dist: paramiko; extra == "ssh"
Provides-Extra: fuse
Requires-Dist: fusepy; extra == "fuse"
Provides-Extra: libarchive
Requires-Dist: libarchive-c; extra == "libarchive"
Provides-Extra: gui
Requires-Dist: panel; extra == "gui"
Provides-Extra: tqdm
Requires-Dist: tqdm; extra == "tqdm"
Provides-Extra: full
Requires-Dist: adlfs; extra == "full"
Requires-Dist: aiohttp!=4.0.0a0,!=4.0.0a1; extra == "full"
Requires-Dist: dask; extra == "full"
Requires-Dist: distributed; extra == "full"
Requires-Dist: dropbox; extra == "full"
Requires-Dist: dropboxdrivefs; extra == "full"
Requires-Dist: fusepy; extra == "full"
Requires-Dist: gcsfs; extra == "full"
Requires-Dist: libarchive-c; extra == "full"
Requires-Dist: ocifs; extra == "full"
Requires-Dist: panel; extra == "full"
Requires-Dist: paramiko; extra == "full"
Requires-Dist: pyarrow>=1; extra == "full"
Requires-Dist: pygit2; extra == "full"
Requires-Dist: requests; extra == "full"
Requires-Dist: s3fs; extra == "full"
Requires-Dist: smbprotocol; extra == "full"
Requires-Dist: tqdm; extra == "full"
Provides-Extra: devel
Requires-Dist: pytest; extra == "devel"
Requires-Dist: pytest-cov; extra == "devel"
